{
    "authors": [],
    "edmundson_summary": [
        "People who survived the journey from Turkey to the Greek island of Lesbos recount their perilous voyage",
        "EU leaders trying to finalise a deal with Turkey on the migrant crisis have warned of the difficulties they face at the start of a summit in Brussels.",
        "German Chancellor Angela Merkel said negotiations would be \"complicated\" but the direction was clear.",
        "A note on terminology: The BBC uses the term migrant to refer to all people on the move who have yet to complete the legal process of claiming asylum.",
        "This group includes people fleeing war-torn countries such as Syria, who are likely to be granted refugee status, as well as people who are seeking jobs and better lives, who governments are likely to rule are economic migrants."
    ],
    "news_brand": "bbc",
    "movies": [],
    "sum-basic_summary": [
        "In return the EU might offer Turkey incentives, including financial aid and visa-free access to Schengen countries.",
        "The aim is to establish a joint position of all 28 EU member states before talks with the Turkish prime minister on Friday.",
        "Since January 2015, a million migrants and refugees have entered the EU by boat from Turkey to Greece.",
        "Image copyright @RPFranceUE",
        "What mattered was \"busting the business model of the people smugglers\"."
    ],
    "meta_keywords": [
        ""
    ],
    "text_teaser_summary": [
        "And Belgian Prime Minister Charles Michel said he could not accept negotiations that looked like blackmail.",
        "In return the EU might offer Turkey incentives, including financial aid and visa-free access to Schengen countries.",
        "The aim is to establish a joint position of all 28 EU member states before talks with the Turkish prime minister on Friday.",
        "The proposed deal would see all migrants travelling to Greece from Turkey sent back.",
        "Under initial proposals, for each Syrian migrant returned to Turkey, a different Syrian would be resettled in the EU directly from the country."
    ],
    "source_url": "http://www.bbc.com",
    "kl_summary": [
        "In return, the EU would double financial aid to Turkey promised last year, make a fresh push on talks over Turkey's eventual membership of the EU and offer visa-free travel to Europe's Schengen states.",
        "Image copyright Getty Images  The migrants' onward travel to northern Europe is now blocked by Balkan border closures",
        "What mattered was \"busting the business model of the people smugglers\".",
        "German magazine Der Spiegel said on Thursday it had withdrawn its Istanbul correspondent, Hasnain Kazim, after the authorities refused to renew his press accreditation.",
        "This group includes people fleeing war-torn countries such as Syria, who are likely to be granted refugee status, as well as people who are seeking jobs and better lives, who governments are likely to rule are economic migrants."
    ],
    "title": "Migrant crisis: EU leaders cautious on Turkey deal",
    "lex-rank_summary": [
        "The proposed deal would see all migrants travelling to Greece from Turkey sent back.",
        "In return the EU might offer Turkey incentives, including financial aid and visa-free access to Schengen countries.",
        "Image copyright AFP  A makeshift camp for refugees at the Greek-Macedonian border is housing thousands",
        "In return, the EU would double financial aid to Turkey promised last year, make a fresh push on talks over Turkey's eventual membership of the EU and offer visa-free travel to Europe's Schengen states.",
        "The Greek Cypriot government is not recognised by Turkey."
    ],
    "luhn_summary": [
        "The proposed deal would see all migrants travelling to Greece from Turkey sent back.",
        "In return the EU might offer Turkey incentives, including financial aid and visa-free access to Schengen countries.",
        "The aim is to establish a joint position of all 28 EU member states before talks with the Turkish prime minister on Friday.",
        "In return, the EU would double financial aid to Turkey promised last year, make a fresh push on talks over Turkey's eventual membership of the EU and offer visa-free travel to Europe's Schengen states.",
        "Image copyright Getty Images  The migrants' onward travel to northern Europe is now blocked by Balkan border closures"
    ],
    "publish_date": {
        "__class__": "datetime",
        "__value__": "2016-03-29T02:25:55.130415"
    },
    "text": " People who survived the journey from Turkey to the Greek island of Lesbos recount their perilous voyage\n\nEU leaders trying to finalise a deal with Turkey on the migrant crisis have warned of the difficulties they face at the start of a summit in Brussels.\n\nGerman Chancellor Angela Merkel said negotiations would be \"complicated\" but the direction was clear.\n\nThe proposed deal would see all migrants travelling to Greece from Turkey sent back.\n\nIn return the EU might offer Turkey incentives, including financial aid and visa-free access to Schengen countries.\n\nThe aim is to establish a joint position of all 28 EU member states before talks with the Turkish prime minister on Friday.\n\nBut Lithuanian President Dalia Grybauskaite warned that the plan to return people to Turkey was \"on the edge of international law\" and difficult to implement. And Belgian Prime Minister Charles Michel said he could not accept negotiations that looked like blackmail.\n\nImage copyright AFP  A makeshift camp for refugees at the Greek-Macedonian border is housing thousands\n\nSince January 2015, a million migrants and refugees have entered the EU by boat from Turkey to Greece. More than 132,000 have arrived this year alone.\n\nTens of thousands are now stuck in Greece as their route north has been blocked.\n\n\"Germany will negotiate intensively because we have to improve the humanitarian situation in Greece,\" Mrs Merkel said.\n\nDutch Prime Minister Mark Rutte said if a deal could be reached the influx of migrants from Turkey to the Greek islands could be stopped \"in three to four weeks\".\n\nUnder initial proposals, for each Syrian migrant returned to Turkey, a different Syrian would be resettled in the EU directly from the country.\n\nIn return, the EU would double financial aid to Turkey promised last year, make a fresh push on talks over Turkey's eventual membership of the EU and offer visa-free travel to Europe's Schengen states.\n\nHowever, those proposals have since been watered down, lowering expectation on greater financial help and talks on EU membership and linking visa-free travel to 72 conditions to which Turkey must agree.\n\nEU member Cyprus has threatened to veto a deal. The Greek Cypriot government is not recognised by Turkey.\n\nThe Spanish foreign minister has said Spain will oppose the \"blanket return\" of refugees to Turkey.\n\nImage copyright Getty Images  The migrants' onward travel to northern Europe is now blocked by Balkan border closures\n\nImage copyright @RPFranceUE\n\nStressing what he called the UK's special status in the EU, Prime Minister David Cameron said he would not be offering visa-free access to Turkey. What mattered was \"busting the business model of the people smugglers\".\n\nA number of EU countries have raised concerns about what is on offer to Turkey amid a clampdown by the Ankara government on academics and journalists.\n\nGerman magazine Der Spiegel said on Thursday it had withdrawn its Istanbul correspondent, Hasnain Kazim, after the authorities refused to renew his press accreditation.\n\nEU foreign policy chief Federica Mogherini said the talks with Turkey would not just focus on migration.\n\n\"We have the internal situation in Turkey we are working on, being it the human rights and the rule of law issues, being it the necessary process with the Kurds to reopen spaces for peace,\" she said.\n\nA note on terminology: The BBC uses the term migrant to refer to all people on the move who have yet to complete the legal process of claiming asylum. This group includes people fleeing war-torn countries such as Syria, who are likely to be granted refugee status, as well as people who are seeking jobs and better lives, who governments are likely to rule are economic migrants.",
    "tags": [],
    "meta_img": "http://ichef-1.bbci.co.uk/news/1024/cpsprodpb/17BC5/production/_88812279_88812278.jpg",
    "images": [
        "http://ssc.api.bbc.com/?c1=2&c2=19293874&ns_site=bbc&name=news.world-europe-35828810",
        "http://ichef-1.bbci.co.uk/news/1024/cpsprodpb/17BC5/production/_88812279_88812278.jpg",
        "http://static.bbci.co.uk/frameworks/barlesque/3.8.0/orb/4/img/bbc-blocks-dark.png",
        "http://stats.bbc.co.uk/o.gif?~RS~s~RS~News~RS~t~RS~HighWeb_Story~RS~i~RS~35828810~RS~p~RS~99123~RS~a~RS~Asia~RS~u~RS~/news/world-europe-35828810~RS~r~RS~0~RS~q~RS~0~RS~z~RS~1865~RS~",
        "http://sa.bbc.co.uk/bbc/bbc/s?name=news.world.europe.story.35828810.page&ml_name=webmodule&ml_version=50&blq_js_enabled=0&blq_s=4d&blq_r=2.7&blq_v=default&blq_e=pal&cps_asset_id=35828810&page_type=Story&section=%2Fnews%2Fworld%2Feurope&first_pub=2016-03-17T01%3A58%3A40%2B00%3A00&last_editorial_update=2016-03-17T17%3A36%3A22%2B00%3A00&curie=a4a9d29b-129f-b643-90f9-757621a6795b&title=Migrant+crisis%3A+EU+leaders+cautious+on+Turkey+deal&has_video=1&topic_names=Europe+migrant+crisis%21Greece%21European+Union%21Turkey&topic_ids=23672ac3-fcad-42c7-a557-23a954eb0e7b%21785b1cd2-db1a-493f-8647-05da1aaef049%219a18805c-fb88-40ba-9763-bcc121d5d55c%21a30418d5-3efe-415d-b2d2-1480eaf2eb4a&for_nation=hk&app_version=1.116.0&bbc_site=news&pal_route=asset&app_type=responsive&language=en-GB&pal_webapp=tabloid&prod_name=news&app_name=news",
        "http://static.bbci.co.uk/frameworks/barlesque/3.8.0/orb/4/img/orb-search-dark.png"
    ],
    "top_image": "http://ichef-1.bbci.co.uk/news/1024/cpsprodpb/17BC5/production/_88812279_88812278.jpg",
    "url": "http://www.bbc.com/news/world-europe-35828810",
    "lsa_summary": [
        "But Lithuanian President Dalia Grybauskaite warned that the plan to return people to Turkey was \"on the edge of international law\" and difficult to implement.",
        "Dutch Prime Minister Mark Rutte said if a deal could be reached the influx of migrants from Turkey to the Greek islands could be stopped \"in three to four weeks\".",
        "However, those proposals have since been watered down, lowering expectation on greater financial help and talks on EU membership and linking visa-free travel to 72 conditions to which Turkey must agree.",
        "German magazine Der Spiegel said on Thursday it had withdrawn its Istanbul correspondent, Hasnain Kazim, after the authorities refused to renew his press accreditation.",
        "\"We have the internal situation in Turkey we are working on, being it the human rights and the rule of law issues, being it the necessary process with the Kurds to reopen spaces for peace,\" she said."
    ],
    "keywords": [
        "deal",
        "greece",
        "prime",
        "cautious",
        "migrants",
        "talks",
        "crisis",
        "turkey",
        "migrant",
        "eu",
        "return",
        "leaders",
        "minister",
        "visafree"
    ],
    "geoLocation": [
        "Turkey",
        "EU",
        "Greece"
    ],
    "text-rank_summary": [
        "In return the EU might offer Turkey incentives, including financial aid and visa-free access to Schengen countries.",
        "Since January 2015, a million migrants and refugees have entered the EU by boat from Turkey to Greece.",
        "Under initial proposals, for each Syrian migrant returned to Turkey, a different Syrian would be resettled in the EU directly from the country.",
        "In return, the EU would double financial aid to Turkey promised last year, make a fresh push on talks over Turkey's eventual membership of the EU and offer visa-free travel to Europe's Schengen states.",
        "Stressing what he called the UK's special status in the EU, Prime Minister David Cameron said he would not be offering visa-free access to Turkey."
    ]
}